doxyphp2sphinx/__init__.py
doxyphp2sphinx/__main__.py
doxyphp2sphinx/cli.py
doxyphp2sphinx/logger.py
doxyphp2sphinx/rstgenerator.py
doxyphp2sphinx-1.0.1.dist-info/DESCRIPTION.rst
doxyphp2sphinx-1.0.1.dist-info/LICENSE.txt
doxyphp2sphinx-1.0.1.dist-info/METADATA
doxyphp2sphinx-1.0.1.dist-info/RECORD
doxyphp2sphinx-1.0.1.dist-info/WHEEL
doxyphp2sphinx-1.0.1.dist-info/entry_points.txt
doxyphp2sphinx-1.0.1.dist-info/metadata.json
doxyphp2sphinx-1.0.1.dist-info/top_level.txt
