Metadata-Version: 2.0
Name: doxyphp2sphinx
Version: 1.0.1
Summary: API Documentation generator for PHP projects which use Sphinx.
Home-page: https://github.com/mike42/doxyphp2sphinx
Author: Michael Billington
Author-email: michael.billington@gmail.com
License: UNKNOWN
Project-URL: Bug Reports, https://github.com/mike42/doxyphp2sphinx/issues
Project-URL: Source, https://github.com/mike42/doxyphp2sphinx
Keywords: doxygen sphinx restructuredtext readthedocs php documentation
Platform: UNKNOWN
Classifier: Development Status :: 3 - Alpha
Classifier: Environment :: Console
Classifier: Intended Audience :: Developers
Classifier: Framework :: Sphinx
Classifier: License :: OSI Approved :: BSD License
Classifier: Operating System :: OS Independent
Classifier: Programming Language :: Python :: 2
Classifier: Programming Language :: Python :: 2.7
Classifier: Programming Language :: Python :: 3
Classifier: Programming Language :: Python :: 3.4
Classifier: Programming Language :: Python :: 3.5
Classifier: Programming Language :: Python :: 3.6
Classifier: Topic :: Software Development
Classifier: Topic :: Software Development :: Documentation
Classifier: Topic :: Documentation
Classifier: Topic :: Documentation :: Sphinx
Classifier: Topic :: Utilities
Provides-Extra: test
Provides-Extra: dev
Requires-Dist: enum34
Provides-Extra: dev
Requires-Dist: check-manifest; extra == 'dev'
Provides-Extra: test
Requires-Dist: coverage; extra == 'test'
